aceinna/__init__.py
aceinna/executor.py
aceinna/bootstrap/__init__.py
aceinna/bootstrap/cli.py
aceinna/bootstrap/default.py
aceinna/bootstrap/loader.py
aceinna/bootstrap/log_parser.py
aceinna/bootstrap/receiver.py
aceinna/core/__init__.py
aceinna/core/device_context.py
aceinna/core/driver.py
aceinna/core/event_base.py
aceinna/core/gnss.py
aceinna/core/packet_statistics.py
aceinna/core/tunnel_base.py
aceinna/core/tunnel_web.py
aceinna/devices/__init__.py
aceinna/devices/decorator.py
aceinna/devices/device_manager.py
aceinna/devices/message_center.py
aceinna/devices/parser_manager.py
aceinna/devices/upgrade_center.py
aceinna/devices/base/__init__.py
aceinna/devices/base/message_parser_base.py
aceinna/devices/base/provider_base.py
aceinna/devices/base/rtk_provider_base.py
aceinna/devices/base/upgrade_worker_base.py
aceinna/devices/configs/__init__.py
aceinna/devices/configs/openimu_predefine.py
aceinna/devices/configs/openrtk_predefine.py
aceinna/devices/dmu/__init__.py
aceinna/devices/dmu/configuration_field.py
aceinna/devices/dmu/dmu_helper.py
aceinna/devices/dmu/eeprom_field.py
aceinna/devices/dmu/uart_provider.py
aceinna/devices/ins2000/__init__.py
aceinna/devices/ins2000/uart_provider.py
aceinna/devices/openimu/__init__.py
aceinna/devices/openimu/uart_provider.py
aceinna/devices/openrtk/__init__.py
aceinna/devices/openrtk/ethernet_provider.py
aceinna/devices/openrtk/lan_provider.py
aceinna/devices/openrtk/uart_provider.py
aceinna/devices/parsers/__init__.py
aceinna/devices/parsers/dmu_field_parser.py
aceinna/devices/parsers/dmu_message_parser.py
aceinna/devices/parsers/dum_packet_parser.py
aceinna/devices/parsers/ins2000_message_parser.py
aceinna/devices/parsers/ins401_field_parser.py
aceinna/devices/parsers/ins401_message_parser.py
aceinna/devices/parsers/ins401_packet_parser.py
aceinna/devices/parsers/open_field_parser.py
aceinna/devices/parsers/open_message_parser.py
aceinna/devices/parsers/open_packet_parser.py
aceinna/devices/ping/__init__.py
openimu-2.6.1.dist-info/LICENSE
openimu-2.6.1.dist-info/METADATA
openimu-2.6.1.dist-info/WHEEL
openimu-2.6.1.dist-info/entry_points.txt
openimu-2.6.1.dist-info/top_level.txt
openimu-2.6.1.dist-info/RECORD
